odoo/addons/mgmtsystem_health_safety/README.rst
odoo/addons/mgmtsystem_health_safety/__init__.py
odoo/addons/mgmtsystem_health_safety/__manifest__.py
odoo/addons/mgmtsystem_health_safety/data/health_safety.xml
odoo/addons/mgmtsystem_health_safety/i18n/de.po
odoo/addons/mgmtsystem_health_safety/i18n/fr.po
odoo/addons/mgmtsystem_health_safety/i18n/it.po
odoo/addons/mgmtsystem_health_safety/i18n/mgmtsystem_health_safety.pot
odoo/addons/mgmtsystem_health_safety/i18n/nb.po
odoo/addons/mgmtsystem_health_safety/i18n/pt_BR.po
odoo/addons/mgmtsystem_health_safety/i18n/sv.po
odoo/addons/mgmtsystem_health_safety/i18n/vi.po
odoo/addons/mgmtsystem_health_safety/readme/CONTRIBUTORS.rst
odoo/addons/mgmtsystem_health_safety/readme/DESCRIPTION.rst
odoo/addons/mgmtsystem_health_safety/readme/ROADMAP.rst
odoo/addons/mgmtsystem_health_safety/readme/USAGE.rst
odoo/addons/mgmtsystem_health_safety/static/description/icon.png
odoo/addons/mgmtsystem_health_safety/static/description/index.html
odoo/addons/mgmtsystem_health_safety/static/src/img/icon.png
odoo_addon_mgmtsystem_health_safety-16.0.1.0.1.1.dist-info/METADATA
odoo_addon_mgmtsystem_health_safety-16.0.1.0.1.1.dist-info/WHEEL
odoo_addon_mgmtsystem_health_safety-16.0.1.0.1.1.dist-info/top_level.txt
odoo_addon_mgmtsystem_health_safety-16.0.1.0.1.1.dist-info/RECORD
