Metadata-Version: 2.1
Name: odoo-addon-mgmtsystem-health-safety
Version: 16.0.1.0.1.1
Summary: Health and Safety Management System
Home-page: https://github.com/OCA/management-system
Author: Savoir-faire Linux,Odoo Community Association (OCA)
Author-email: support@odoo-community.org
License: AGPL-3
Platform: UNKNOWN
Classifier: Programming Language :: Python
Classifier: Framework :: Odoo
Classifier: Framework :: Odoo :: 16.0
Classifier: License :: OSI Approved :: GNU Affero General Public License v3
Requires-Python: >=3.10
Requires-Dist: odoo-addon-document-page-health-safety-manual <16.1dev,>=16.0dev
Requires-Dist: odoo-addon-mgmtsystem-audit <16.1dev,>=16.0dev
Requires-Dist: odoo-addon-mgmtsystem-hazard-risk <16.1dev,>=16.0dev
Requires-Dist: odoo-addon-mgmtsystem-manual <16.1dev,>=16.0dev
Requires-Dist: odoo-addon-mgmtsystem-review <16.1dev,>=16.0dev
Requires-Dist: odoo <16.1dev,>=16.0a
